[{"id":1,"name":"ramin farzadmehr 2","username":"ramin 22","email":"Julianne.OConner@kory.org 2","phone":"1234512342","website":"dijikala.com","extension":"jpg"},{"id":2,"name":"ramin2 farzadmehr","username":"ramin2","email":"Julianne.OConner@kory.org","phone":"123451234","website":"php.com","extension":"jpg"},{"id":3,"name":"ramin3 farzadmehr","username":"Karianne","email":"Julianne.OConner@kory.org","phone":"123451234","website":"laravel.com","extension":"jpg"},{"name":"farshad","username":"azimi","email":"farshad@gmail.com","phone":"25616166","website":"w3school.com","id":3609260}]